{
  "id": "4021692",
  "name": "noxone",
  "font_family": "iconfont",
  "css_prefix_text": "icon-",
  "description": "",
  "glyphs": [
    {
      "icon_id": "1029",
      "name": "音乐",
      "font_class": "yinle",
      "unicode": "e600",
      "unicode_decimal": 58880
    },
    {
      "icon_id": "444564",
      "name": "播放",
      "font_class": "bofang",
      "unicode": "e66a",
      "unicode_decimal": 58986
    },
    {
      "icon_id": "444577",
      "name": "暂停",
      "font_class": "zanting",
      "unicode": "e677",
      "unicode_decimal": 58999
    },
    {
      "icon_id": "10622217",
      "name": "音乐",
      "font_class": "dilanxianxingiconyihuifu_huabanfuben",
      "unicode": "e602",
      "unicode_decimal": 58882
    },
    {
      "icon_id": "20736099",
      "name": "下一首",
      "font_class": "xiayishou",
      "unicode": "e6ae",
      "unicode_decimal": 59054
    },
    {
      "icon_id": "20784230",
      "name": "上一首歌",
      "font_class": "shangyishouge",
      "unicode": "e6bf",
      "unicode_decimal": 59071
    }
  ]
}
